concentrator/README.rst
concentrator/__init__.py
concentrator/app_meta.py
concentrator/apps.py
concentrator/change.py
concentrator/concentrator.conf.default
concentrator/constants.py
concentrator/exceptions.py
concentrator/models.py
concentrator/rules.py
concentrator/settings.py
concentrator/tasks.py
concentrator/wsfactory_config.xml.default
concentrator/changes/__init__.py
concentrator/changes/actions.py
concentrator/changes/app_meta.py
concentrator/changes/constants.py
concentrator/changes/forms.py
concentrator/changes/helpers.py
concentrator/changes/rules.py
concentrator/changes/reports/__init__.py
concentrator/changes/reports/report.py
concentrator/changes/reports/templates/changes.xls
concentrator/changes/reports/templates/changes_blank.xls
concentrator/dict/__init__.py
concentrator/dict/actions.py
concentrator/dict/constants.py
concentrator/dict/forms.py
concentrator/dict/proxy.py
concentrator/dict/signal_handlers.py
concentrator/dict/signals.py
concentrator/dict/tests/__init__.py
concentrator/dict/tests/tests.py
concentrator/management/__init__.py
concentrator/management/commands/__init__.py
concentrator/management/commands/delete_empty_changedeclarations.py
concentrator/management/commands/delete_excluded_units_from_concentrator.py
concentrator/management/commands/delete_invalid_changes.py
concentrator/management/commands/process_404_declarations.py
concentrator/management/commands/send_dicts_to_concentrator.py
concentrator/migrations/0001_initial.py
concentrator/migrations/0002_auto_20170206_1055.py
concentrator/migrations/0003_privilegecomment.py
concentrator/migrations/0004_migrate_privileges.py
concentrator/migrations/0005_migrate_model_fields_in_changedeclaration.py
concentrator/migrations/0006_auto_20191126_1358.py
concentrator/migrations/0007_alter_delegateperson_delegate.py
concentrator/migrations/__init__.py
concentrator/smev3/__init__.py
concentrator/smev3/app_meta.py
concentrator/smev3/apps.py
concentrator/smev3/extensions.py
concentrator-2.48.0.dist-info/METADATA
concentrator-2.48.0.dist-info/WHEEL
concentrator-2.48.0.dist-info/top_level.txt
concentrator-2.48.0.dist-info/RECORD
